{
  "tasks": {
    "dev": "deno run --allow-all libs/tests/start.ts",
    "lint": "deno lint",
    "test": "deno test --allow-all",
    "test:ci": "deno test --allow-all --trace-ops"
  },
  "importMap": "./.vscode/import-map.json",
  "compilerOptions": {
    "strictPropertyInitialization": false,
    "lib": [
      "dom",
      "dom.iterable",
      "deno.ns"
    ]
  },
  "lint": {
    "files": {
      "exclude": [
        "./npm"
      ]
    }
  },
  "fmt": {
    "files": {
      "exclude": [
        "./npm"
      ]
    },
    "options": {
      "singleQuote": true,
      "semiColons": false
    }
  },
  "test": {
    "files": {
      "exclude": [
        "./npm"
      ]
    }
  }
}